empty/__init__.py
asbestos_snow-1.6.1.dist-info/METADATA
asbestos_snow-1.6.1.dist-info/WHEEL
asbestos_snow-1.6.1.dist-info/RECORD
