Metadata-Version: 2.3
Name: asbestos-snow
Version: 1.6.1
Summary: asbestos-snow has moved to asbestos: https://pypi.org/project/asbestos/
Author: Joe Kaufeld
Author-email: jkaufeld@spoton.com
Requires-Python: >=3.9,<4.0
Classifier: Programming Language :: Python :: 3
Classifier: Programming Language :: Python :: 3.9
Classifier: Programming Language :: Python :: 3.10
Classifier: Programming Language :: Python :: 3.11
Classifier: Programming Language :: Python :: 3.12
Classifier: Programming Language :: Python :: 3.13
Requires-Dist: asbestos (==1.6.1)
